react_bucket_deployment/__init__.py
cdk_react_bucket_deployment-0.1.1.dist-info/LICENSE
cdk_react_bucket_deployment-0.1.1.dist-info/METADATA
cdk_react_bucket_deployment-0.1.1.dist-info/WHEEL
cdk_react_bucket_deployment-0.1.1.dist-info/RECORD
