Metadata-Version: 2.1
Name: cdk-react-bucket-deployment
Version: 0.1.1
Summary: A custom AWS CDK construct that integrates node for building react projects and deploying them to AWS S3.
License: MIT
Author: TCL Research Europe
Author-email: tcl.research.eu@gmail.com
Requires-Python: >=3.12,<4.0
Classifier: License :: OSI Approved :: MIT License
Classifier: Programming Language :: Python :: 3
Classifier: Programming Language :: Python :: 3.12
Requires-Dist: aws-cdk-lib (>=2.130.0,<3.0.0)
Requires-Dist: constructs (>=10.3.0,<11.0.0)
